wcpms/__init__.py
wcpms/wcpms.py
wcpms-0.3.2.dist-info/licenses/LICENSE
wcpms-0.3.2.dist-info/METADATA
wcpms-0.3.2.dist-info/WHEEL
wcpms-0.3.2.dist-info/top_level.txt
wcpms-0.3.2.dist-info/RECORD
