Metadata-Version: 2.4
Name: wcpms
Version: 0.3.2
Summary: Python Client of the Web Crop Phenological Metrics Service for Earth Observation Data Cubes
Home-page: https://github.com/brazil-data-cube/wcpms.py
Author: Brazil Data Cube Team
Author-email: bdc.team@inpe.br
License-File: LICENSE
Requires-Dist: urllib3==2.2.2
Requires-Dist: requests==2.32.3
Requires-Dist: pandas==2.2.2
Requires-Dist: plotly==6.0.1
Requires-Dist: scipy==1.13.1
Requires-Dist: datetime==5.5
Requires-Dist: geopandas==1.0.1
Provides-Extra: docs
Requires-Dist: Sphinx>=2.2; extra == "docs"
Requires-Dist: sphinx_rtd_theme; extra == "docs"
Requires-Dist: sphinx-copybutton; extra == "docs"
Provides-Extra: all
Requires-Dist: Sphinx>=2.2; extra == "all"
Requires-Dist: sphinx_rtd_theme; extra == "all"
Requires-Dist: sphinx-copybutton; extra == "all"
Dynamic: author
Dynamic: author-email
Dynamic: description
Dynamic: home-page
Dynamic: license-file
Dynamic: provides-extra
Dynamic: requires-dist
Dynamic: summary
